captchaai_python/__init__.py
captchaai_python/antiakamai_bmp.py
captchaai_python/antikasada.py
captchaai_python/captchaai.py
captchaai_python/datadome_slider.py
captchaai_python/fun_captcha.py
captchaai_python/funcaptcha_classification.py
captchaai_python/gee_test.py
captchaai_python/h_captcha.py
captchaai_python/hcaptcha_classification.py
captchaai_python/image_to_text.py
captchaai_python/proxy.py
captchaai_python/recaptcha_v2.py
captchaai_python/recaptcha_v2_enterprise.py
captchaai_python/recaptcha_v3.py
captchaai_python/request_type.py
captchaai_python/useragent.py
captchaai_python/utils.py
captchaai_python-1.0.dist-info/LICENSE
captchaai_python-1.0.dist-info/METADATA
captchaai_python-1.0.dist-info/WHEEL
captchaai_python-1.0.dist-info/top_level.txt
captchaai_python-1.0.dist-info/RECORD
