Metadata-Version: 2.1
Name: captchaai-python
Version: 1.0
Summary: CaptchaAI.IO library for Python
Home-page: https://github.com/alperensert/captchaai_python
Author: Alperen Sert
Author-email: business@alperenn.com
License: MIT
Project-URL: Documentation, https://github.com/alperensert/captchaai_python/wiki/
Project-URL: Source, https://github.com/alperensert/captchaai_python/
Project-URL: Tracker, https://github.com/alperensert/captchaai_python/issues
Classifier: Development Status :: 4 - Beta
Classifier: License :: OSI Approved :: MIT License
Classifier: Programming Language :: Python :: 3
Classifier: Programming Language :: Python :: 3.6
Classifier: Programming Language :: Python :: 3.7
Classifier: Programming Language :: Python :: 3.8
Classifier: Programming Language :: Python :: 3.9
Requires: requests
Requires-Python: >=3
License-File: LICENSE
Requires-Dist: requests
Requires-Dist: six
